airfs/__init__.py
airfs/_automount/__init__.py
airfs/_automount/github.py
airfs/_core/__init__.py
airfs/_core/cache.py
airfs/_core/compat.py
airfs/_core/config.py
airfs/_core/exceptions.py
airfs/_core/functions_core.py
airfs/_core/functions_extra.py
airfs/_core/functions_io.py
airfs/_core/functions_os.py
airfs/_core/functions_os_path.py
airfs/_core/functions_shutil.py
airfs/_core/io_base.py
airfs/_core/io_base_buffered.py
airfs/_core/io_base_raw.py
airfs/_core/io_base_system.py
airfs/_core/io_random_write.py
airfs/_core/storage_manager.py
airfs/config.py
airfs/io.py
airfs/os/__init__.py
airfs/os/path.py
airfs/shutil.py
airfs/storage/__init__.py
airfs/storage/azure.py
airfs/storage/azure_blob/__init__.py
airfs/storage/azure_blob/_append_blob.py
airfs/storage/azure_blob/_base_blob.py
airfs/storage/azure_blob/_block_blob.py
airfs/storage/azure_blob/_page_blob.py
airfs/storage/azure_blob/_system.py
airfs/storage/azure_file.py
airfs/storage/github/__init__.py
airfs/storage/github/_client.py
airfs/storage/github/_model.py
airfs/storage/github/_model_archive.py
airfs/storage/github/_model_base.py
airfs/storage/github/_model_git.py
airfs/storage/github/_model_reference.py
airfs/storage/github/_model_release.py
airfs/storage/http.py
airfs/storage/oss.py
airfs/storage/s3.py
airfs/storage/swift.py
airfs-1.5.2.dist-info/LICENSE
airfs-1.5.2.dist-info/METADATA
airfs-1.5.2.dist-info/WHEEL
airfs-1.5.2.dist-info/RECORD
