Metadata-Version: 2.1
Name: airfs
Version: 1.5.2
Summary: A Python library for cloud and remote file Systems.
Home-page: https://github.com/JGoutin/airfs
License: Apache License, Version 2.0
Keywords: file-system,storage,io,stream,cloud,cloud-storage,blob,bucket,alibaba,aws,azure,github,http,openstack,oss,s3,swift,minio
Author: J.Goutin
Requires-Python: >=3.8,<4.0
Classifier: Development Status :: 5 - Production/Stable
Classifier: Intended Audience :: Developers
Classifier: License :: OSI Approved :: Apache Software License
Classifier: License :: Other/Proprietary License
Classifier: Operating System :: OS Independent
Classifier: Programming Language :: Python
Classifier: Programming Language :: Python :: 3
Classifier: Programming Language :: Python :: 3.8
Classifier: Programming Language :: Python :: 3.9
Classifier: Programming Language :: Python :: 3.10
Classifier: Programming Language :: Python :: 3.11
Classifier: Programming Language :: Python :: 3
Classifier: Programming Language :: Python :: 3.10
Classifier: Programming Language :: Python :: 3.11
Classifier: Programming Language :: Python :: 3.8
Classifier: Programming Language :: Python :: 3.9
Classifier: Topic :: System :: Filesystems
Provides-Extra: all
Provides-Extra: azure-blob
Provides-Extra: azure-file
Provides-Extra: oss
Provides-Extra: s3
Provides-Extra: swift
Requires-Dist: azure-storage-blob (>=2,<3) ; extra == "all" or extra == "azure-blob"
Requires-Dist: azure-storage-file (>=2,<3) ; extra == "all" or extra == "azure-file"
Requires-Dist: boto3 (>=1.26,<2.0) ; extra == "all" or extra == "s3"
Requires-Dist: oss2 (>=2.15,<3.0) ; extra == "all" or extra == "oss"
Requires-Dist: python-dateutil
Requires-Dist: python-swiftclient[keystone] (>=4,<5) ; extra == "all" or extra == "swift"
Requires-Dist: requests
Project-URL: Documentation, https://jgoutin.github.io/airfs/
Project-URL: Repository, https://github.com/JGoutin/airfs
